data_designer/errors.py
data_designer/lazy_heavy_imports.py
data_designer/logging.py
data_designer/plugin_manager.py
data_designer/config/__init__.py
data_designer/config/_version.py
data_designer/config/base.py
data_designer/config/column_configs.py
data_designer/config/column_types.py
data_designer/config/config_builder.py
data_designer/config/data_designer_config.py
data_designer/config/dataset_builders.py
data_designer/config/dataset_metadata.py
data_designer/config/default_model_settings.py
data_designer/config/errors.py
data_designer/config/interface.py
data_designer/config/models.py
data_designer/config/preview_results.py
data_designer/config/processors.py
data_designer/config/run_config.py
data_designer/config/sampler_constraints.py
data_designer/config/sampler_params.py
data_designer/config/seed.py
data_designer/config/seed_source.py
data_designer/config/seed_source_types.py
data_designer/config/validator_params.py
data_designer/config/analysis/__init__.py
data_designer/config/analysis/column_profilers.py
data_designer/config/analysis/column_statistics.py
data_designer/config/analysis/dataset_profiler.py
data_designer/config/analysis/utils/errors.py
data_designer/config/analysis/utils/reporting.py
data_designer/config/testing/__init__.py
data_designer/config/testing/fixtures.py
data_designer/config/utils/code_lang.py
data_designer/config/utils/constants.py
data_designer/config/utils/errors.py
data_designer/config/utils/info.py
data_designer/config/utils/io_helpers.py
data_designer/config/utils/misc.py
data_designer/config/utils/numerical_helpers.py
data_designer/config/utils/type_helpers.py
data_designer/config/utils/visualization.py
data_designer/plugins/__init__.py
data_designer/plugins/errors.py
data_designer/plugins/plugin.py
data_designer/plugins/registry.py
data_designer_config-0.4.0.dist-info/METADATA
data_designer_config-0.4.0.dist-info/WHEEL
data_designer_config-0.4.0.dist-info/RECORD
