Metadata-Version: 2.4
Name: data-designer-config
Version: 0.4.0
Summary: Configuration layer for DataDesigner synthetic data generation
License-Expression: Apache-2.0
Classifier: Development Status :: 4 - Beta
Classifier: Intended Audience :: Developers
Classifier: Intended Audience :: Science/Research
Classifier: License :: OSI Approved :: Apache Software License
Classifier: Programming Language :: Python :: 3.10
Classifier: Programming Language :: Python :: 3.11
Classifier: Programming Language :: Python :: 3.12
Classifier: Programming Language :: Python :: 3.13
Classifier: Topic :: Scientific/Engineering :: Artificial Intelligence
Requires-Python: >=3.10
Requires-Dist: jinja2<4,>=3.1.6
Requires-Dist: numpy<3,>=1.23.5
Requires-Dist: pandas<3,>=2.3.3
Requires-Dist: pyarrow<20,>=19.0.1
Requires-Dist: pydantic[email]<3,>=2.9.2
Requires-Dist: pygments<3,>=2.19.2
Requires-Dist: python-json-logger<4,>=3
Requires-Dist: pyyaml<7,>=6.0.1
Requires-Dist: rich<15,>=13.7.1
